shgpy/__init__.py
shgpy/fformfit.py
shgpy/fformgen.py
shgpy/formgen.py
shgpy/plotter.py
shgpy/shg_symbols.py
shgpy/tensor_definitions.py
shgpy/core/__init__.py
shgpy/core/_fourier_transform.py
shgpy/core/_lookup_table.py
shgpy/core/data_handler.py
shgpy/core/utilities.py
tests/__init__.py
tests/test_data_handler.py
tests/test_deepcopy.py
tests/test_fformfit.py
tests/test_fformgen.py
tests/test_formgen.py
tests/test_merge_containers.py
tests/test_pickle.py
shgpy-0.8.6.dist-info/LICENSE
shgpy-0.8.6.dist-info/METADATA
shgpy-0.8.6.dist-info/WHEEL
shgpy-0.8.6.dist-info/top_level.txt
shgpy-0.8.6.dist-info/RECORD
