Metadata-Version: 2.1
Name: shgpy
Version: 0.8.6
Summary: A collection of utilities for analyzing SHG data.
Home-page: https://bfichera.github.io/shgpy/
Author: Bryan Fichera
Author-email: bfichera@mit.edu
Classifier: Programming Language :: Python :: 3
Classifier: License :: OSI Approved :: MIT License
Classifier: Operating System :: OS Independent
Requires-Python: >=3.6
License-File: LICENSE
Requires-Dist: pandas
Requires-Dist: sympy
Requires-Dist: scipy
Requires-Dist: matplotlib
